{"transaction_id":"699d7bce9091689de1e2a01a","external_id":"538571719301f8151375904226b3594cc32cd090f3d6eeb34bc618eb2b11986b","amount":3.9900000000000002131628207280300557613372802734375,"product_name":"Privacy - Plano Mensal","created_at_utc":"2026-02-24 10:22:05","customer":{"name":"Heberto emanuel talis lima de jesus","email":"talizbob@icloud.com","phone":"5575982805402","cpf":"13432030908","client_ip_address":null},"tracking":{"src":null,"sck":null,"utm_source":null,"utm_campaign":null,"utm_medium":null,"utm_content":null,"utm_term":null}}