{"transaction_id":"69a268f9d114ad6e7eb378d6","external_id":"6943b5b59007ac89886e94e765e026a31c5e0a4f82c8a64c5cd3293b5e1fcd80","amount":6.9900000000000002131628207280300557613372802734375,"product_name":"Privacy - Plano Mensal","created_at_utc":"2026-02-28 04:03:03","customer":{"name":"Lucas Patrick Pinheiro da Silva","email":"Lucaspk1512@gmail.com","phone":"559191441980","cpf":"13432030908","client_ip_address":null},"tracking":{"src":null,"sck":null,"utm_source":null,"utm_campaign":null,"utm_medium":null,"utm_content":null,"utm_term":null}}