{"transaction_id":"69a2a313d114ad6e7eb38967","external_id":"0c14b3a446be70f258a458f5fa0b0ec6b65e2690d441201f3f1b9d3c8b94e229","amount":23.78999999999999914734871708787977695465087890625,"product_name":"Privacy - Plano Mensal + Maisa Silva + Nicolle Ex do Gordão","created_at_utc":"2026-02-28 08:10:57","customer":{"name":"Adilson jesus da silva","email":"godinho50cent@gmail.com","phone":"5511987198007","cpf":"13432030908","client_ip_address":null},"tracking":{"src":null,"sck":null,"utm_source":null,"utm_campaign":null,"utm_medium":null,"utm_content":null,"utm_term":null}}