{"transaction_id":"69a2ad03d114ad6e7eb38c56","external_id":"163244e9ed2463e75455771d7b45633e19e3490f37d5bf4602ecbd613bba5ace","amount":14.8900000000000005684341886080801486968994140625,"product_name":"Privacy - Plano Mensal + Maisa Silva","created_at_utc":"2026-02-28 08:53:18","customer":{"name":"Beto da Silva Oliveira","email":"betodasilvaoliveira46@gmail.com","phone":"5592985951925","cpf":"13432030908","client_ip_address":null},"tracking":{"src":null,"sck":null,"utm_source":null,"utm_campaign":null,"utm_medium":null,"utm_content":null,"utm_term":null}}